Metadata-Version: 2.1
Name: overgang
Version: 0.3.0
Summary: (deprecated package) Markov Modeling
Home-page: http://github.com/kmedian/overgang
Author: Ulf Hamster
Author-email: 554c46@gmail.com
License: MIT
Platform: UNKNOWN
Requires-Python: >=3
